cells_detection/__init__.py
cells_detection/data_loader.py
cells_detection/fct.py
cells_detection/ki67_segmentation.py
cells_detection/segmentation.py
cells_detection/utils.py
seg/__init__.py
seg/data_loader.py
seg/fct.py
seg/ki67_segmentation.py
seg/segmentation.py
seg/utils.py
ki67segmentation-0.0.2.dist-info/METADATA
ki67segmentation-0.0.2.dist-info/WHEEL
ki67segmentation-0.0.2.dist-info/top_level.txt
ki67segmentation-0.0.2.dist-info/RECORD
