Metadata-Version: 2.1
Name: ki67segmentation
Version: 0.0.2
Summary: UNKNOWN
Home-page: https://github.com/AntoineRouland/ki67_pack
Author: Rouland Antoine
Author-email: antoine.rouland@grenoble-inp.org
License: UNKNOWN
Platform: UNKNOWN
Classifier: Programming Language :: Python :: 3
Classifier: License :: OSI Approved :: MIT License
Classifier: Operating System :: OS Independent
